LICENSE.md
MANIFEST.in
README.md
dynamic_extras_require.txt
dynamic_install_requires.txt
quicklib_incorporated.v2.5.zip
quicklib_setup_from_yml.py
epic/serialize/__init__.py
epic/serialize/__version__.py
epic/serialize/registrar.py
epic/serialize/spoc.py
epic/serialize/compressors/__init__.py
epic/serialize/compressors/base.py
epic/serialize/compressors/lz4.py
epic/serialize/serializers/__init__.py
epic/serialize/serializers/base.py
epic/serialize/serializers/dill.py
epic/serialize/tests/__init__.py
epic/serialize/tests/test_spoc.py
epic_serialize.egg-info/PKG-INFO
epic_serialize.egg-info/SOURCES.txt
epic_serialize.egg-info/dependency_links.txt
epic_serialize.egg-info/requires.txt
epic_serialize.egg-info/top_level.txt