Metadata-Version: 2.1
Name: epic-serialize
Version: 1.0
Summary: Easy serialization of Python objects with multiprocessing support
Home-page: https://github.com/Cybereason/epic-serialize
Author: Uri Sternfeld, Assaf Ben-David, Yonatan Perry
License: MIT License
Platform: UNKNOWN
Classifier: Development Status :: 4 - Beta
Classifier: Intended Audience :: Developers
Classifier: Operating System :: POSIX :: Linux
Classifier: Operating System :: MacOS :: MacOS X
Classifier: Operating System :: Microsoft :: Windows
Classifier: Programming Language :: Python :: 3 :: Only
Classifier: Programming Language :: Python :: 3.10
Requires-Python: >=3.10
License-File: LICENSE.md
